codantic/__init__.py
codantic/__main__.py
codantic/app.py
codantic/core/__init__.py
codantic/core/annotation.py
codantic/core/bbox.py
codantic/core/category.py
codantic/core/coco.py
codantic/core/image.py
codantic/core/video.py
codantic/evaluator/__init__.py
codantic/evaluator/object_detector.py
codantic/models/__init__.py
codantic/models/base.py
codantic/models/face_detection.py
codantic/models/image_captioning.py
codantic/models/object_detection.py
codantic-0.0.9.dist-info/LICENSE.txt
codantic-0.0.9.dist-info/METADATA
codantic-0.0.9.dist-info/WHEEL
codantic-0.0.9.dist-info/entry_points.txt
codantic-0.0.9.dist-info/top_level.txt
codantic-0.0.9.dist-info/RECORD
