Metadata-Version: 2.1
Name: codantic
Version: 0.0.9
Summary: CocoDataset reader
Home-page: UNKNOWN
Author: nghoangdat
Author-email: 18.hoang.dat.12@gmail.com
License: UNKNOWN
Platform: UNKNOWN
Classifier: Programming Language :: Python :: 3
Classifier: License :: OSI Approved :: MIT License
Classifier: Operating System :: OS Independent
License-File: LICENSE.txt
Requires-Dist: mousse
Requires-Dist: pandas
Requires-Dist: pycocotools
Provides-Extra: all
